baserow_dynamic_table/__init__.py
baserow_dynamic_table/apps.py
baserow_dynamic_table/models.py
baserow_dynamic_table/populate.py
baserow_dynamic_table/rows.py
baserow_dynamic_table/types.py
baserow_dynamic_table/validators.py
baserow_dynamic_table/core/__init__.py
baserow_dynamic_table/core/constants.py
baserow_dynamic_table/core/db.py
baserow_dynamic_table/core/expressions.py
baserow_dynamic_table/core/fields.py
baserow_dynamic_table/core/mixins.py
baserow_dynamic_table/core/registry.py
baserow_dynamic_table/core/utils.py
baserow_dynamic_table/db/__init__.py
baserow_dynamic_table/db/aggregations.py
baserow_dynamic_table/db/atomic.py
baserow_dynamic_table/db/schema.py
baserow_dynamic_table/db/sql_queries.py
baserow_dynamic_table/fields/__init__.py
baserow_dynamic_table/fields/deferred_field_fk_updater.py
baserow_dynamic_table/fields/exceptions.py
baserow_dynamic_table/fields/expressions.py
baserow_dynamic_table/fields/field_cache.py
baserow_dynamic_table/fields/field_converters.py
baserow_dynamic_table/fields/field_filters.py
baserow_dynamic_table/fields/field_helpers.py
baserow_dynamic_table/fields/field_sortings.py
baserow_dynamic_table/fields/field_types.py
baserow_dynamic_table/fields/fields.py
baserow_dynamic_table/fields/handler.py
baserow_dynamic_table/fields/mixins.py
baserow_dynamic_table/fields/models.py
baserow_dynamic_table/fields/registries.py
baserow_dynamic_table/fields/dependencies/__init__.py
baserow_dynamic_table/fields/dependencies/circular_reference_checker.py
baserow_dynamic_table/fields/dependencies/dependency_rebuilder.py
baserow_dynamic_table/fields/dependencies/exceptions.py
baserow_dynamic_table/fields/dependencies/handler.py
baserow_dynamic_table/fields/dependencies/models.py
baserow_dynamic_table/fields/dependencies/types.py
baserow_dynamic_table/fields/dependencies/update_collector.py
baserow_dynamic_table/management/__init__.py
baserow_dynamic_table/management/commands/__init__.py
baserow_dynamic_table-0.1.0.dist-info/METADATA
baserow_dynamic_table-0.1.0.dist-info/WHEEL
baserow_dynamic_table-0.1.0.dist-info/RECORD
