Metadata-Version: 2.1
Name: baserow-dynamic-table
Version: 0.1.0
Summary: Add your description here
Author-email: Tobi DEGNON <tobidegnon@proton.me>
Requires-Python: >=3.8
Requires-Dist: django>=4.2.6
Requires-Dist: djangorestframework>=3.14.0
Requires-Dist: faker>=19.12.0
Requires-Dist: hiredis>=2.2.3
Requires-Dist: loguru>=0.7.2
Requires-Dist: psycopg2>=2.9.9
Requires-Dist: redis>=5.0.1
Requires-Dist: regex>=2023.10.3
Requires-Dist: typing-extensions>=4.8.0
